sanic_quill/__init__.py
sanic_quill/fields/tabs.py
sanic_quill/fields/wysiwyg.py
sanic_quill/form.py
sanic_quill/routes.py
sanic_quill/static/editor/editor.js
sanic_quill/static/editor/view-quill.css
sanic_quill/static/tabs/tabs.css
sanic_quill/static/tabs/tabs.js
sanic_quill/template.py
sanic_quill/templates/base.html
sanic_quill/templates/dependencies.html
sanic_quill/templates/edit.html
sanic_quill/templates/layout.html
sanic_quill/templates/lib.html
sanic_quill/templates/master.html
sanic_quill/widgets/__init__.py
sanic_quill/widgets/tabs.py
sanic_quill-0.0.2.dist-info/WHEEL
sanic_quill-0.0.2.dist-info/METADATA
sanic_quill-0.0.2.dist-info/RECORD
