Metadata-Version: 2.1
Name: sanic-quill
Version: 0.0.2
Summary: Sanic-quill is a port of Flask-quill to Sanic ecosystem. (quill.js WYSIWYG editor)
License: MIT
Author: xnuinside
Author-email: xnuinside@gmail.com
Requires-Python: >=3.7,<4.0
Classifier: License :: OSI Approved :: MIT License
Classifier: Programming Language :: Python :: 3
Classifier: Programming Language :: Python :: 3.7
Classifier: Programming Language :: Python :: 3.8
Requires-Dist: Sanic-Jinja2 (>=0.8.0,<0.9.0)
Requires-Dist: wtforms (>=2.3.1,<3.0.0)
